babelplot/__init__.py
babelplot/version.py
babelplot/api/type.py
babelplot/backend/catalog/bokeh_.py
babelplot/backend/catalog/matplotlib_.py
babelplot/backend/catalog/plotly_.py
babelplot/backend/catalog/vedo_.py
babelplot/backend/helper/creation.py
babelplot/backend/helper/validation.py
babelplot/constant/backend.py
babelplot/constant/path.py
babelplot/constant/project.py
babelplot/extension/enum_.py
babelplot/extension/function.py
babelplot/runtime/backends.py
babelplot/task/help.py
babelplot/task/instantiation.py
babelplot/task/plotting.py
babelplot/task/showing.py
babelplot/type/backend.py
babelplot/type/dimension.py
babelplot/type/ffp_base.py
babelplot/type/figure.py
babelplot/type/frame.py
babelplot/type/plot.py
babelplot/type/plot_function.py
babelplot/type/plot_type.py
babelplot/type/translator.py
babelplot-2025.14.dist-info/METADATA
babelplot-2025.14.dist-info/WHEEL
babelplot-2025.14.dist-info/top_level.txt
babelplot-2025.14.dist-info/RECORD
