Metadata-Version: 2.4
Name: babelplot
Version: 2025.14
Summary: A Meta Plotting Library That Speaks Several Backends
Home-page: https://src.koda.cnrs.fr/eric.debreuve/babelplot/
Author: Eric Debreuve
Author-email: eric.debreuve@cnrs.fr
License: CeCILL-2.1
Project-URL: Documentation, https://src.koda.cnrs.fr/eric.debreuve/babelplot/-/wikis/home
Project-URL: Source, https://src.koda.cnrs.fr/eric.debreuve/babelplot/
Keywords: plot,library
Classifier: Topic :: Scientific/Engineering :: Visualization
Classifier: Intended Audience :: Science/Research
Classifier: License :: OSI Approved :: CEA CNRS Inria Logiciel Libre License, version 2.1 (CeCILL-2.1)
Classifier: Programming Language :: Python :: 3
Classifier: Development Status :: 3 - Alpha
Requires-Python: >=3.11
Requires-Dist: color_spec_changer
Requires-Dist: numpy
Requires-Dist: scikit-image
Dynamic: author
Dynamic: author-email
Dynamic: classifier
Dynamic: description
Dynamic: description-content-type
Dynamic: home-page
Dynamic: keywords
Dynamic: license
Dynamic: project-url
Dynamic: requires-dist
Dynamic: requires-python
Dynamic: summary
